med_interact
