Metadata-Version: 2.1
Name: med-interact
Version: 0.0.2
Summary: Python library to check drug interactions, side effects and harmful effects.
Home-page: https://github.com/isranetoo/med-interact
Author: DrugXpert
Author-email: contact@medinteract.com
Classifier: Programming Language :: Python :: 3
Classifier: License :: OSI Approved :: MIT License
License-File: LICENSE
